streamlit_navigation_bar/__init__.py
streamlit_navigation_bar/__main__.py
streamlit_navigation_bar/errors.py
streamlit_navigation_bar/example.py
streamlit_navigation_bar/match_navbar.py
streamlit_navigation_bar/frontend/dist/index.html
streamlit_navigation_bar/frontend/dist/assets/index-gNq6KwcW.css
streamlit_navigation_bar/frontend/dist/assets/index-pkw_XHPT.js
streamlit_navigation_bar/templates/base.css
streamlit_navigation_bar/templates/options.css
streamlit_navigation_bar-3.3.0.dist-info/LICENSE
streamlit_navigation_bar-3.3.0.dist-info/METADATA
streamlit_navigation_bar-3.3.0.dist-info/WHEEL
streamlit_navigation_bar-3.3.0.dist-info/entry_points.txt
streamlit_navigation_bar-3.3.0.dist-info/top_level.txt
streamlit_navigation_bar-3.3.0.dist-info/RECORD
