Metadata-Version: 2.1
Name: streamlit-navigation-bar
Version: 3.3.0
Summary: A component that allows you to place a navigation bar in your Streamlit app.
Home-page: https://github.com/gabrieltempass/streamlit-navigation-bar
Author: Gabriel Tem Pass
Author-email: redo_hint_0x@icloud.com
License: MIT License
Project-URL: Source Code, https://github.com/gabrieltempass/streamlit-navigation-bar
Project-URL: Bug Tracker, https://github.com/gabrieltempass/streamlit-navigation-bar/issues
Project-URL: Release notes, https://github.com/gabrieltempass/streamlit-navigation-bar/releases
Project-URL: Documentation, https://github.com/gabrieltempass/streamlit-navigation-bar/wiki/API-reference
Project-URL: Community, https://discuss.streamlit.io/t/new-component-streamlit-navigation-bar/66032
Platform: UNKNOWN
Classifier: Development Status :: 5 - Production/Stable
Classifier: Environment :: Console
Classifier: Environment :: Web Environment
Classifier: Intended Audience :: Developers
Classifier: Intended Audience :: Science/Research
Classifier: License :: OSI Approved :: MIT License
Classifier: Programming Language :: Python :: 3.8
Classifier: Programming Language :: Python :: 3.9
Classifier: Programming Language :: Python :: 3.10
Classifier: Programming Language :: Python :: 3.11
Classifier: Programming Language :: Python :: 3.12
Classifier: Topic :: Database :: Front-Ends
Classifier: Topic :: Office/Business :: Financial :: Spreadsheet
Classifier: Topic :: Scientific/Engineering :: Information Analysis
Classifier: Topic :: Scientific/Engineering :: Visualization
Classifier: Topic :: Software Development :: Libraries :: Application Frameworks
Classifier: Topic :: Software Development :: Widget Sets
Requires-Python: >=3.8
License-File: LICENSE
